{"r32": [{"match_id": "M73", "idx": 0, "slot_a": "2A", "slot_b": "2B", "slot_a_teams": [{"team": "South Africa", "p": 1.0}], "slot_b_teams": [{"team": "Canada", "p": 1.0}]}, {"match_id": "M74", "idx": 1, "slot_a": "1E", "slot_b": "3rd:ABCDF", "slot_a_teams": [{"team": "Germany", "p": 1.0}], "slot_b_teams": [{"team": "Bosnia-Herzegovina", "p": 0.339}, {"team": "Paraguay", "p": 0.246}, {"team": "Scotland", "p": 0.17}]}, {"match_id": "M75", "idx": 2, "slot_a": "1F", "slot_b": "2C", "slot_a_teams": [{"team": "Netherlands", "p": 0.681}, {"team": "Japan", "p": 0.303}, {"team": "Sweden", "p": 0.016}], "slot_b_teams": [{"team": "Morocco", "p": 1.0}]}, {"match_id": "M76", "idx": 3, "slot_a": "1C", "slot_b": "2F", "slot_a_teams": [{"team": "Brazil", "p": 1.0}], "slot_b_teams": [{"team": "Japan", "p": 0.594}, {"team": "Netherlands", "p": 0.319}, {"team": "Sweden", "p": 0.088}]}, {"match_id": "M77", "idx": 4, "slot_a": "1I", "slot_b": "3rd:CDFGH", "slot_a_teams": [{"team": "France", "p": 0.955}, {"team": "Norway", "p": 0.045}], "slot_b_teams": [{"team": "Paraguay", "p": 0.215}, {"team": "Sweden", "p": 0.187}, {"team": "Egypt", "p": 0.161}]}, {"match_id": "M78", "idx": 5, "slot_a": "2E", "slot_b": "2I", "slot_a_teams": [{"team": "Ivory Coast", "p": 0.901}, {"team": "Curacao", "p": 0.083}, {"team": "Ecuador", "p": 0.016}], "slot_b_teams": [{"team": "Norway", "p": 0.955}, {"team": "France", "p": 0.045}]}, {"match_id": "M79", "idx": 6, "slot_a": "1A", "slot_b": "3rd:CEFHI", "slot_a_teams": [{"team": "Mexico", "p": 1.0}], "slot_b_teams": [{"team": "Senegal", "p": 0.269}, {"team": "Sweden", "p": 0.259}, {"team": "Scotland", "p": 0.201}]}, {"match_id": "M80", "idx": 7, "slot_a": "1L", "slot_b": "3rd:EHIJK", "slot_a_teams": [{"team": "England", "p": 0.866}, {"team": "Croatia", "p": 0.123}, {"team": "Ghana", "p": 0.011}], "slot_b_teams": [{"team": "DR Congo", "p": 0.418}, {"team": "Senegal", "p": 0.186}, {"team": "Algeria", "p": 0.162}]}, {"match_id": "M81", "idx": 8, "slot_a": "1D", "slot_b": "3rd:BEFIJ", "slot_a_teams": [{"team": "USA", "p": 1.0}], "slot_b_teams": [{"team": "Bosnia-Herzegovina", "p": 0.661}, {"team": "Sweden", "p": 0.095}, {"team": "Algeria", "p": 0.088}]}, {"match_id": "M82", "idx": 9, "slot_a": "1G", "slot_b": "3rd:AEHIJ", "slot_a_teams": [{"team": "Egypt", "p": 0.583}, {"team": "Belgium", "p": 0.271}, {"team": "Iran", "p": 0.147}], "slot_b_teams": [{"team": "South Korea", "p": 0.831}, {"team": "Senegal", "p": 0.056}, {"team": "Algeria", "p": 0.041}]}, {"match_id": "M83", "idx": 10, "slot_a": "2K", "slot_b": "2L", "slot_a_teams": [{"team": "Portugal", "p": 0.554}, {"team": "Colombia", "p": 0.444}, {"team": "DR Congo", "p": 0.002}], "slot_b_teams": [{"team": "Croatia", "p": 0.689}, {"team": "Ghana", "p": 0.177}, {"team": "England", "p": 0.134}]}, {"match_id": "M84", "idx": 11, "slot_a": "1H", "slot_b": "2J", "slot_a_teams": [{"team": "Spain", "p": 0.81}, {"team": "Uruguay", "p": 0.174}, {"team": "Cape Verde", "p": 0.016}], "slot_b_teams": [{"team": "Austria", "p": 0.718}, {"team": "Algeria", "p": 0.282}]}, {"match_id": "M85", "idx": 12, "slot_a": "1B", "slot_b": "3rd:EFGIJ", "slot_a_teams": [{"team": "Switzerland", "p": 1.0}], "slot_b_teams": [{"team": "Algeria", "p": 0.19}, {"team": "Sweden", "p": 0.188}, {"team": "Senegal", "p": 0.167}]}, {"match_id": "M86", "idx": 13, "slot_a": "1J", "slot_b": "2H", "slot_a_teams": [{"team": "Argentina", "p": 1.0}], "slot_b_teams": [{"team": "Saudi Arabia", "p": 0.447}, {"team": "Cape Verde", "p": 0.351}, {"team": "Spain", "p": 0.149}]}, {"match_id": "M87", "idx": 14, "slot_a": "1K", "slot_b": "3rd:DEIJL", "slot_a_teams": [{"team": "Colombia", "p": 0.556}, {"team": "Portugal", "p": 0.444}], "slot_b_teams": [{"team": "Ghana", "p": 0.811}, {"team": "Croatia", "p": 0.182}, {"team": "Paraguay", "p": 0.002}]}, {"match_id": "M88", "idx": 15, "slot_a": "2D", "slot_b": "2G", "slot_a_teams": [{"team": "Australia", "p": 0.889}, {"team": "Paraguay", "p": 0.111}], "slot_b_teams": [{"team": "Belgium", "p": 0.633}, {"team": "Iran", "p": 0.19}, {"team": "Egypt", "p": 0.153}]}], "team_paths": {"Mexico": {"r32": {"Senegal": 0.269, "Sweden": 0.2587, "Scotland": 0.2008, "Ecuador": 0.0779, "Uruguay": 0.0665}, "r16": {"England": 0.5095, "Croatia": 0.0618, "Senegal": 0.0257, "DR Congo": 0.0245, "Algeria": 0.0141}, "qf": {"Brazil": 0.1192, "Japan": 0.031, "Norway": 0.0265, "Netherlands": 0.0239, "France": 0.0048}, "sf": {"Argentina": 0.0341, "Colombia": 0.0099, "Portugal": 0.0096, "Belgium": 0.0068, "Switzerland": 0.0033}, "final": {"France": 0.0042, "Spain": 0.0029, "Germany": 0.0029, "Netherlands": 0.0022, "Portugal": 0.0018}}, "South Africa": {"r32": {"Canada": 1.0}, "r16": {"Netherlands": 0.1231, "Morocco": 0.1101, "Japan": 0.0507, "Sweden": 0.0012}, "qf": {"France": 0.0215, "Germany": 0.0163, "South Korea": 0.0004, "Bosnia-Herzegovina": 0.0004, "Spain": 0.0003}, "sf": {"Spain": 0.0014, "USA": 0.001, "Portugal": 0.0006, "South Korea": 0.0005, "Colombia": 0.0003}, "final": {"England": 0.0008, "Argentina": 0.0002}}, "South Korea": {"r32": {"Egypt": 0.4935, "Belgium": 0.2204, "Iran": 0.117, "Germany": 0.1153}, "r16": {"USA": 0.4416, "Bosnia-Herzegovina": 0.0624, "France": 0.021, "Senegal": 0.0143, "Sweden": 0.0118}, "qf": {"Spain": 0.1098, "Portugal": 0.0442, "Colombia": 0.0324, "Croatia": 0.0157, "Uruguay": 0.0146}, "sf": {"France": 0.0246, "Germany": 0.0136, "Netherlands": 0.0076, "Morocco": 0.0046, "Japan": 0.003}, "final": {"Argentina": 0.0034, "England": 0.0025, "Brazil": 0.002, "Portugal": 0.0014, "Colombia": 0.0007}}, "Czech Republic": {"r32": {}, "r16": {}, "qf": {}, "sf": {}, "final": {}}, "Canada": {"r32": {"South Africa": 1.0}, "r16": {"Netherlands": 0.3206, "Morocco": 0.2713, "Japan": 0.1201, "Sweden": 0.0029}, "qf": {"France": 0.0951, "Germany": 0.0691, "Spain": 0.0016, "South Korea": 0.0015, "Sweden": 0.0013}, "sf": {"Spain": 0.0106, "USA": 0.0045, "Portugal": 0.0044, "Colombia": 0.0023, "Croatia": 0.0013}, "final": {"England": 0.0016, "Argentina": 0.0015, "Brazil": 0.0009, "Belgium": 0.0005, "Colombia": 0.0004}}, "Bosnia-Herzegovina": {"r32": {"USA": 0.6609, "Germany": 0.3391}, "r16": {"South Korea": 0.0624, "France": 0.0327, "Belgium": 0.0208, "Egypt": 0.0177, "Senegal": 0.0052}, "qf": {"Spain": 0.018, "Portugal": 0.0082, "Colombia": 0.0049, "Croatia": 0.0025, "Netherlands": 0.002}, "sf": {"France": 0.0018, "Germany": 0.0014, "Netherlands": 0.001, "Morocco": 0.0006, "Spain": 0.0006}, "final": {"Brazil": 0.0001, "Spain": 0.0001, "Croatia": 0.0001, "England": 0.0001, "Netherlands": 0.0001}}, "Qatar": {"r32": {}, "r16": {}, "qf": {}, "sf": {}, "final": {}}, "Switzerland": {"r32": {"Algeria": 0.1896, "Sweden": 0.1879, "Senegal": 0.1667, "Iran": 0.1484, "Austria": 0.1144}, "r16": {"Colombia": 0.3252, "Portugal": 0.2677, "Ghana": 0.0524, "Croatia": 0.0408, "Senegal": 0.0003}, "qf": {"Argentina": 0.1473, "Belgium": 0.0387, "Australia": 0.0128, "Spain": 0.0105, "Uruguay": 0.0025}, "sf": {"Brazil": 0.02, "England": 0.0192, "Mexico": 0.0033, "Japan": 0.0029, "Netherlands": 0.0027}, "final": {"France": 0.0029, "Spain": 0.0026, "Netherlands": 0.0023, "Germany": 0.0019, "Portugal": 0.001}}, "Brazil": {"r32": {"Japan": 0.5935, "Netherlands": 0.3189, "Sweden": 0.0876}, "r16": {"Norway": 0.474, "Ivory Coast": 0.1547, "France": 0.0259, "Curacao": 0.006, "Ecuador": 0.006}, "qf": {"England": 0.3408, "Mexico": 0.1192, "Croatia": 0.0282, "Senegal": 0.0222, "Uruguay": 0.015}, "sf": {"Argentina": 0.1644, "Colombia": 0.047, "Portugal": 0.046, "Belgium": 0.0315, "Switzerland": 0.02}, "final": {"France": 0.0467, "Spain": 0.036, "Germany": 0.0229, "Portugal": 0.0152, "Netherlands": 0.0148}}, "Morocco": {"r32": {"Netherlands": 0.6806, "Japan": 0.303, "Sweden": 0.0164}, "r16": {"Canada": 0.2713, "South Africa": 0.1101}, "qf": {"France": 0.1581, "Germany": 0.1053, "Japan": 0.0029, "Uruguay": 0.0025, "Norway": 0.0023}, "sf": {"Spain": 0.0275, "USA": 0.015, "Portugal": 0.0112, "Colombia": 0.0069, "Belgium": 0.005}, "final": {"Argentina": 0.0099, "England": 0.0062, "Brazil": 0.0034, "Portugal": 0.0026, "Colombia": 0.0019}}, "Haiti": {"r32": {}, "r16": {}, "qf": {}, "sf": {}, "final": {}}, "Scotland": {"r32": {"Mexico": 0.2008, "Germany": 0.1702, "France": 0.0583, "Norway": 0.0029}, "r16": {"England": 0.0343, "France": 0.0167, "Germany": 0.0066, "Croatia": 0.0043, "Senegal": 0.0037}, "qf": {"Brazil": 0.0042, "Netherlands": 0.003, "Japan": 0.0013, "Morocco": 0.0008, "Canada": 0.0005}, "sf": {"Argentina": 0.0011, "Spain": 0.0005, "Belgium": 0.0003, "Colombia": 0.0002, "South Korea": 0.0001}, "final": {"Spain": 0.0001, "Argentina": 0.0001}}, "USA": {"r32": {"Bosnia-Herzegovina": 0.6609, "Sweden": 0.0949, "Algeria": 0.0883, "Senegal": 0.0797, "Austria": 0.0547}, "r16": {"South Korea": 0.4416, "Belgium": 0.1534, "Egypt": 0.1057, "Senegal": 0.0293, "Iran": 0.0253}, "qf": {"Spain": 0.2393, "Portugal": 0.1055, "Colombia": 0.0679, "Croatia": 0.0383, "Uruguay": 0.0308}, "sf": {"France": 0.0694, "Germany": 0.0459, "Netherlands": 0.0255, "Morocco": 0.015, "Japan": 0.0093}, "final": {"Argentina": 0.0169, "England": 0.012, "Brazil": 0.0107, "Portugal": 0.005, "Colombia": 0.0038}}, "Paraguay": {"r32": {"Germany": 0.2464, "France": 0.2047, "Belgium": 0.0708, "Iran": 0.0208, "Egypt": 0.0166}, "r16": {"France": 0.0197, "Argentina": 0.019, "Germany": 0.0178, "Spain": 0.0018, "Saudi Arabia": 0.0016}, "qf": {"Portugal": 0.0014, "Morocco": 0.0014, "Netherlands": 0.0012, "Switzerland": 0.0009, "Colombia": 0.0009}, "sf": {"Spain": 0.0001, "Netherlands": 0.0001, "Brazil": 0.0001, "Colombia": 0.0001, "Portugal": 0.0001}, "final": {}}, "Australia": {"r32": {"Belgium": 0.5622, "Iran": 0.1694, "Egypt": 0.1363, "Germany": 0.0497, "France": 0.0428}, "r16": {"Argentina": 0.281, "Spain": 0.0219, "Saudi Arabia": 0.0135, "Cape Verde": 0.0112, "France": 0.0051}, "qf": {"Colombia": 0.0174, "Portugal": 0.0167, "Switzerland": 0.0128, "Croatia": 0.0019, "Belgium": 0.0014}, "sf": {"Brazil": 0.0044, "England": 0.0043, "Netherlands": 0.001, "Mexico": 0.0009, "Japan": 0.0005}, "final": {"Germany": 0.0005, "France": 0.0004, "Colombia": 0.0002, "Spain": 0.0002, "Belgium": 0.0001}}, "Turkey": {"r32": {}, "r16": {}, "qf": {}, "sf": {}, "final": {}}, "Germany": {"r32": {"Bosnia-Herzegovina": 0.3391, "Paraguay": 0.2464, "Scotland": 0.1702, "South Korea": 0.1153, "Sweden": 0.062}, "r16": {"France": 0.7221, "Norway": 0.0257, "Sweden": 0.0214, "Paraguay": 0.0178, "Uruguay": 0.0174}, "qf": {"Netherlands": 0.1369, "Morocco": 0.1053, "Canada": 0.0691, "Japan": 0.0528, "South Africa": 0.0163}, "sf": {"Spain": 0.0892, "USA": 0.0459, "Portugal": 0.0352, "Colombia": 0.0209, "South Korea": 0.0136}, "final": {"Argentina": 0.0432, "Brazil": 0.0229, "England": 0.0222, "Portugal": 0.0091, "Colombia": 0.0082}}, "Curacao": {"r32": {"Norway": 0.0793, "Mexico": 0.0089, "France": 0.004, "England": 0.0034, "Switzerland": 0.0015}, "r16": {"Brazil": 0.006, "Japan": 0.0017, "Netherlands": 0.0006, "England": 0.0004, "Croatia": 0.0002}, "qf": {"England": 0.0006, "Croatia": 0.0002, "Brazil": 0.0002, "Senegal": 0.0001, "Uruguay": 0.0001}, "sf": {"Argentina": 0.0001, "Belgium": 0.0001, "Portugal": 0.0001}, "final": {}}, "Ivory Coast": {"r32": {"Norway": 0.861, "France": 0.0397, "Switzerland": 0.0228, "Mexico": 0.0157, "USA": 0.0156}, "r16": {"Brazil": 0.1547, "Japan": 0.0429, "Netherlands": 0.0353, "Sweden": 0.0022, "Mexico": 0.0018}, "qf": {"England": 0.0157, "Mexico": 0.0047, "Senegal": 0.0011, "Croatia": 0.0011, "Ecuador": 0.0007}, "sf": {"Argentina": 0.0014, "Belgium": 0.0006, "Portugal": 0.0006, "Spain": 0.0004, "Colombia": 0.0003}, "final": {"Spain": 0.0002, "Portugal": 0.0002, "France": 0.0002, "England": 0.0001, "Germany": 0.0001}}, "Ecuador": {"r32": {"Mexico": 0.0779, "England": 0.0317, "Norway": 0.0149, "Switzerland": 0.0066, "Croatia": 0.0052}, "r16": {"England": 0.0296, "Mexico": 0.0061, "Brazil": 0.006, "Croatia": 0.0049, "USA": 0.003}, "qf": {"Brazil": 0.0092, "Norway": 0.0026, "Netherlands": 0.0023, "Japan": 0.0019, "England": 0.0015}, "sf": {"Argentina": 0.0039, "Colombia": 0.0013, "Portugal": 0.0008, "Belgium": 0.0006, "Spain": 0.0003}, "final": {"France": 0.0006, "Spain": 0.0004, "USA": 0.0003, "Portugal": 0.0003, "Germany": 0.0003}}, "Netherlands": {"r32": {"Morocco": 0.6806, "Brazil": 0.3189, "France": 0.0002, "USA": 0.0001, "Switzerland": 0.0001}, "r16": {"Canada": 0.3206, "South Africa": 0.1231, "Norway": 0.0925, "Ivory Coast": 0.0353, "France": 0.006}, "qf": {"France": 0.205, "Germany": 0.1369, "England": 0.0653, "Mexico": 0.0239, "Uruguay": 0.0068}, "sf": {"Spain": 0.0601, "Portugal": 0.0299, "Argentina": 0.0287, "USA": 0.0255, "Colombia": 0.0233}, "final": {"Argentina": 0.024, "England": 0.0157, "Brazil": 0.0148, "France": 0.0095, "Portugal": 0.0083}}, "Japan": {"r32": {"Brazil": 0.5935, "Morocco": 0.303, "France": 0.0455, "Mexico": 0.0308, "Germany": 0.0173}, "r16": {"Norway": 0.1338, "Canada": 0.1201, "South Africa": 0.0507, "Ivory Coast": 0.0429, "England": 0.0134}, "qf": {"England": 0.0871, "France": 0.0706, "Germany": 0.0528, "Mexico": 0.031, "Croatia": 0.0072}, "sf": {"Argentina": 0.0312, "Spain": 0.018, "Portugal": 0.0153, "Colombia": 0.0116, "Belgium": 0.0098}, "final": {"Argentina": 0.0066, "France": 0.0058, "Spain": 0.0047, "England": 0.0045, "Portugal": 0.0038}}, "Sweden": {"r32": {"Mexico": 0.2587, "Switzerland": 0.1879, "France": 0.1778, "USA": 0.0949, "Brazil": 0.0876}, "r16": {"England": 0.0484, "Colombia": 0.0285, "Portugal": 0.0219, "Germany": 0.0214, "South Korea": 0.0118}, "qf": {"Argentina": 0.0083, "Brazil": 0.007, "Netherlands": 0.0038, "Spain": 0.003, "Japan": 0.0029}, "sf": {"Argentina": 0.0018, "Portugal": 0.0008, "Colombia": 0.0008, "Spain": 0.0006, "England": 0.0005}, "final": {"Brazil": 0.0003, "Germany": 0.0002, "France": 0.0002, "Spain": 0.0002, "England": 0.0001}}, "Tunisia": {"r32": {}, "r16": {}, "qf": {}, "sf": {}, "final": {}}, "Belgium": {"r32": {"Australia": 0.5622, "South Korea": 0.2204, "Paraguay": 0.0708, "Switzerland": 0.0422, "France": 0.0205}, "r16": {"Argentina": 0.4457, "USA": 0.1534, "Spain": 0.0365, "Bosnia-Herzegovina": 0.0208, "Saudi Arabia": 0.0187}, "qf": {"Portugal": 0.0778, "Colombia": 0.0733, "Spain": 0.056, "Switzerland": 0.0387, "Croatia": 0.0166}, "sf": {"England": 0.0353, "Brazil": 0.0315, "France": 0.0218, "Germany": 0.0128, "Netherlands": 0.0124}, "final": {"France": 0.0111, "Spain": 0.0098, "Argentina": 0.0075, "England": 0.007, "Germany": 0.0052}}, "Egypt": {"r32": {"South Korea": 0.4935, "France": 0.1539, "Australia": 0.1363, "Switzerland": 0.103, "Senegal": 0.0273}, "r16": {"USA": 0.1057, "Argentina": 0.0471, "Bosnia-Herzegovina": 0.0177, "Germany": 0.0142, "Colombia": 0.0095}, "qf": {"Spain": 0.0107, "Portugal": 0.0074, "Colombia": 0.0055, "Argentina": 0.002, "Switzerland": 0.0019}, "sf": {"France": 0.0008, "Brazil": 0.0007, "Netherlands": 0.0005, "Germany": 0.0005, "England": 0.0002}, "final": {"Argentina": 0.0001, "Japan": 0.0001}}, "Iran": {"r32": {"Australia": 0.1694, "Switzerland": 0.1484, "South Korea": 0.117, "France": 0.0915, "Paraguay": 0.0208}, "r16": {"Argentina": 0.0523, "USA": 0.0253, "Colombia": 0.0116, "Portugal": 0.0081, "Germany": 0.0081}, "qf": {"Portugal": 0.004, "Colombia": 0.0033, "Spain": 0.0025, "Argentina": 0.0021, "Switzerland": 0.0017}, "sf": {"Brazil": 0.0008, "Germany": 0.0003, "Croatia": 0.0002, "England": 0.0002, "Mexico": 0.0002}, "final": {"France": 0.0001, "Spain": 0.0001}}, "New Zealand": {"r32": {"Australia": 0.0209, "Switzerland": 0.0046, "France": 0.0041, "Paraguay": 0.003}, "r16": {"Argentina": 0.0036, "Portugal": 0.0003, "Spain": 0.0003, "Colombia": 0.0002, "Germany": 0.0002}, "qf": {"Switzerland": 0.0002, "Portugal": 0.0001, "Austria": 0.0001}, "sf": {"England": 0.0001}, "final": {}}, "Spain": {"r32": {"Austria": 0.5801, "Algeria": 0.2301, "Argentina": 0.1487, "France": 0.0245, "Mexico": 0.0074}, "r16": {"Portugal": 0.2915, "Colombia": 0.2029, "Croatia": 0.1588, "England": 0.0614, "Belgium": 0.0365}, "qf": {"USA": 0.2393, "South Korea": 0.1098, "Belgium": 0.056, "Colombia": 0.0194, "Bosnia-Herzegovina": 0.018}, "sf": {"France": 0.1496, "Germany": 0.0892, "Netherlands": 0.0601, "Morocco": 0.0275, "Japan": 0.018}, "final": {"Argentina": 0.0725, "England": 0.0414, "Brazil": 0.036, "Portugal": 0.0176, "Colombia": 0.0154}}, "Cape Verde": {"r32": {"Argentina": 0.3506, "Mexico": 0.0286, "France": 0.0236, "England": 0.0163, "Austria": 0.0125}, "r16": {"Belgium": 0.0159, "Australia": 0.0112, "England": 0.0024, "Iran": 0.0021, "USA": 0.0016}, "qf": {"Colombia": 0.0017, "Portugal": 0.001, "Switzerland": 0.0007, "Brazil": 0.0004, "Ghana": 0.0002}, "sf": {"Netherlands": 0.0002, "France": 0.0001, "Brazil": 0.0001, "Croatia": 0.0001}, "final": {"Germany": 0.0002}}, "Saudi Arabia": {"r32": {"Argentina": 0.4466, "France": 0.0407, "Mexico": 0.0347, "England": 0.0196, "Croatia": 0.0028}, "r16": {"Belgium": 0.0187, "Australia": 0.0135, "England": 0.0035, "Germany": 0.0034, "Iran": 0.0029}, "qf": {"Colombia": 0.0025, "Portugal": 0.0022, "Switzerland": 0.0016, "Japan": 0.0005, "Uruguay": 0.0003}, "sf": {"Brazil": 0.0004, "England": 0.0003, "Argentina": 0.0003, "Norway": 0.0002, "Netherlands": 0.0002}, "final": {"Germany": 0.0002, "Spain": 0.0001}}, "Uruguay": {"r32": {"Austria": 0.1249, "France": 0.0671, "Mexico": 0.0665, "Argentina": 0.0541, "Algeria": 0.0487}, "r16": {"Portugal": 0.0556, "England": 0.0439, "Colombia": 0.0404, "Croatia": 0.0338, "Germany": 0.0174}, "qf": {"USA": 0.0308, "Brazil": 0.015, "South Korea": 0.0146, "Belgium": 0.007, "Netherlands": 0.0068}, "sf": {"France": 0.017, "Germany": 0.009, "Netherlands": 0.0069, "Argentina": 0.0062, "Portugal": 0.0031}, "final": {"Argentina": 0.0041, "England": 0.0032, "Spain": 0.0031, "Brazil": 0.0023, "France": 0.0018}}, "France": {"r32": {"Paraguay": 0.2047, "Sweden": 0.1778, "Egypt": 0.1539, "Iran": 0.0915, "Uruguay": 0.0671}, "r16": {"Germany": 0.7221, "Bosnia-Herzegovina": 0.0327, "Brazil": 0.0259, "South Korea": 0.021, "Paraguay": 0.0197}, "qf": {"Netherlands": 0.205, "Morocco": 0.1581, "Canada": 0.0951, "Japan": 0.0706, "South Africa": 0.0215}, "sf": {"Spain": 0.1496, "USA": 0.0694, "Portugal": 0.0594, "Colombia": 0.0385, "South Korea": 0.0246}, "final": {"Argentina": 0.0816, "England": 0.0533, "Brazil": 0.0467, "Portugal": 0.0185, "Colombia": 0.0183}}, "Senegal": {"r32": {"Mexico": 0.269, "Switzerland": 0.1667, "England": 0.1604, "USA": 0.0797, "Egypt": 0.0273}, "r16": {"England": 0.0796, "Colombia": 0.0327, "USA": 0.0293, "Portugal": 0.0265, "Mexico": 0.0257}, "qf": {"Brazil": 0.0222, "Spain": 0.0108, "Argentina": 0.0103, "Japan": 0.007, "Netherlands": 0.0054}, "sf": {"Argentina": 0.0051, "France": 0.0021, "Portugal": 0.0019, "Colombia": 0.0019, "Netherlands": 0.0013}, "final": {"Spain": 0.0007, "Portugal": 0.0006, "France": 0.0006, "Argentina": 0.0004, "USA": 0.0003}}, "Iraq": {"r32": {"Switzerland": 0.0054, "USA": 0.0021, "England": 0.0014, "Mexico": 0.0009, "Croatia": 0.0001}, "r16": {"Colombia": 0.0005, "Portugal": 0.0002, "Spain": 0.0001, "England": 0.0001, "Mexico": 0.0001}, "qf": {"Brazil": 0.0001}, "sf": {}, "final": {}}, "Norway": {"r32": {"Ivory Coast": 0.861, "Curacao": 0.0793, "Ecuador": 0.0149, "Paraguay": 0.0108, "Sweden": 0.009}, "r16": {"Brazil": 0.474, "Japan": 0.1338, "Netherlands": 0.0925, "Germany": 0.0257, "Sweden": 0.0068}, "qf": {"England": 0.0723, "Mexico": 0.0265, "Croatia": 0.0071, "Senegal": 0.0047, "Uruguay": 0.004}, "sf": {"Argentina": 0.0132, "Colombia": 0.0047, "Portugal": 0.0042, "Belgium": 0.0026, "Spain": 0.0018}, "final": {"France": 0.0015, "Spain": 0.0012, "Germany": 0.0006, "Netherlands": 0.0006, "Morocco": 0.0005}}, "Argentina": {"r32": {"Saudi Arabia": 0.4466, "Cape Verde": 0.3506, "Spain": 0.1487, "Uruguay": 0.0541}, "r16": {"Belgium": 0.4457, "Australia": 0.281, "Iran": 0.0523, "Egypt": 0.0471, "Paraguay": 0.019}, "qf": {"Colombia": 0.2482, "Portugal": 0.2021, "Switzerland": 0.1473, "Croatia": 0.0263, "Senegal": 0.0103}, "sf": {"England": 0.1836, "Brazil": 0.1644, "Mexico": 0.0341, "Japan": 0.0312, "Netherlands": 0.0287}, "final": {"France": 0.0816, "Spain": 0.0725, "Germany": 0.0432, "Netherlands": 0.024, "Portugal": 0.0217}}, "Algeria": {"r32": {"Spain": 0.2301, "Switzerland": 0.1896, "England": 0.1407, "USA": 0.0883, "Uruguay": 0.0487}, "r16": {"Portugal": 0.0357, "Colombia": 0.0357, "USA": 0.0167, "Mexico": 0.0141, "South Korea": 0.0102}, "qf": {"Argentina": 0.0071, "Spain": 0.0053, "Brazil": 0.005, "Belgium": 0.0035, "USA": 0.0026}, "sf": {"France": 0.0011, "Argentina": 0.0009, "Germany": 0.0009, "Brazil": 0.0009, "Netherlands": 0.0008}, "final": {"England": 0.0002, "Argentina": 0.0002, "Morocco": 0.0001, "Colombia": 0.0001, "Germany": 0.0001}}, "Austria": {"r32": {"Spain": 0.5801, "Uruguay": 0.1249, "Switzerland": 0.1144, "USA": 0.0547, "England": 0.049}, "r16": {"Colombia": 0.0551, "Portugal": 0.0539, "Croatia": 0.0277, "USA": 0.0126, "South Korea": 0.009}, "qf": {"USA": 0.0128, "Argentina": 0.0077, "South Korea": 0.0045, "Spain": 0.004, "Belgium": 0.0037}, "sf": {"France": 0.0037, "Germany": 0.002, "Netherlands": 0.0014, "Morocco": 0.0006, "Brazil": 0.0003}, "final": {"Argentina": 0.0004, "Colombia": 0.0002, "Brazil": 0.0001, "Spain": 0.0001, "Portugal": 0.0001}}, "Jordan": {"r32": {}, "r16": {}, "qf": {}, "sf": {}, "final": {}}, "Portugal": {"r32": {"Ghana": 0.4643, "Croatia": 0.4603, "England": 0.0732, "Paraguay": 0.0007, "Senegal": 0.0005}, "r16": {"Spain": 0.2915, "Switzerland": 0.2677, "Uruguay": 0.0556, "Austria": 0.0539, "Algeria": 0.0357}, "qf": {"Argentina": 0.2021, "USA": 0.1055, "Belgium": 0.0778, "South Korea": 0.0442, "Australia": 0.0167}, "sf": {"France": 0.0594, "England": 0.0527, "Brazil": 0.046, "Germany": 0.0352, "Netherlands": 0.0299}, "final": {"Argentina": 0.0217, "France": 0.0185, "Spain": 0.0176, "Brazil": 0.0152, "England": 0.0147}}, "DR Congo": {"r32": {"England": 0.365, "Croatia": 0.0514, "Ghana": 0.0035}, "r16": {"Mexico": 0.0245, "Senegal": 0.0048, "Uruguay": 0.0016, "Sweden": 0.0012, "Ecuador": 0.001}, "qf": {"Brazil": 0.0016, "Japan": 0.0006, "Norway": 0.0005, "Netherlands": 0.0002, "France": 0.0001}, "sf": {"Argentina": 0.0001, "Colombia": 0.0001, "Croatia": 0.0001}, "final": {}}, "Uzbekistan": {"r32": {"England": 0.0245, "Croatia": 0.0036, "Ghana": 0.0005}, "r16": {"Mexico": 0.0014, "Sweden": 0.0005, "Senegal": 0.0001}, "qf": {"Brazil": 0.0001, "Netherlands": 0.0001}, "sf": {}, "final": {}}, "Colombia": {"r32": {"Ghana": 0.5246, "Croatia": 0.4098, "England": 0.0619, "Paraguay": 0.0012, "Australia": 0.0006}, "r16": {"Switzerland": 0.3252, "Spain": 0.2029, "Austria": 0.0551, "Uruguay": 0.0404, "Algeria": 0.0357}, "qf": {"Argentina": 0.2482, "Belgium": 0.0733, "USA": 0.0679, "South Korea": 0.0324, "Spain": 0.0194}, "sf": {"England": 0.0511, "Brazil": 0.047, "France": 0.0385, "Netherlands": 0.0233, "Germany": 0.0209}, "final": {"France": 0.0183, "Spain": 0.0154, "Portugal": 0.0139, "Argentina": 0.0112, "England": 0.009}}, "England": {"r32": {"DR Congo": 0.365, "Senegal": 0.1604, "Algeria": 0.1407, "Portugal": 0.0732, "Colombia": 0.0619}, "r16": {"Mexico": 0.5095, "Senegal": 0.0796, "Spain": 0.0614, "Sweden": 0.0484, "Uruguay": 0.0439}, "qf": {"Brazil": 0.3408, "Japan": 0.0871, "Norway": 0.0723, "Netherlands": 0.0653, "USA": 0.0219}, "sf": {"Argentina": 0.1836, "Portugal": 0.0527, "Colombia": 0.0511, "Belgium": 0.0353, "Switzerland": 0.0192}, "final": {"France": 0.0533, "Spain": 0.0414, "Germany": 0.0222, "Netherlands": 0.0157, "Portugal": 0.0147}}, "Croatia": {"r32": {"Portugal": 0.4603, "Colombia": 0.4098, "DR Congo": 0.0514, "Senegal": 0.0235, "Algeria": 0.02}, "r16": {"Spain": 0.1588, "Mexico": 0.0618, "Switzerland": 0.0408, "Uruguay": 0.0338, "Austria": 0.0277}, "qf": {"USA": 0.0383, "Brazil": 0.0282, "Argentina": 0.0263, "Belgium": 0.0166, "South Korea": 0.0157}, "sf": {"France": 0.0148, "Argentina": 0.0075, "Germany": 0.0071, "Netherlands": 0.007, "England": 0.0042}, "final": {"Argentina": 0.0034, "France": 0.0031, "England": 0.003, "Spain": 0.0021, "Brazil": 0.0018}}, "Ghana": {"r32": {"Colombia": 0.5246, "Portugal": 0.4643, "DR Congo": 0.0035, "Senegal": 0.0022, "Algeria": 0.0013}, "r16": {"Switzerland": 0.0524, "Spain": 0.0097, "Austria": 0.0059, "Senegal": 0.0055, "Algeria": 0.0052}, "qf": {"Argentina": 0.0102, "Belgium": 0.0024, "USA": 0.0011, "Australia": 0.0008, "Spain": 0.0006}, "sf": {"Brazil": 0.0005, "England": 0.0005, "Netherlands": 0.0003, "Norway": 0.0001, "Uruguay": 0.0001}, "final": {"France": 0.0002, "Colombia": 0.0001, "Netherlands": 0.0001}}, "Panama": {"r32": {}, "r16": {}, "qf": {}, "sf": {}, "final": {}}}}