{"snapshots": [{"ts": "2026-06-28T04:16:57Z", "label": "Live", "probs": {"Argentina": 0.2195, "France": 0.1428, "Spain": 0.1086, "England": 0.0759, "Brazil": 0.0727, "Colombia": 0.0578, "Portugal": 0.0518, "Netherlands": 0.0464, "Germany": 0.0364, "Morocco": 0.0314, "Japan": 0.0272, "Mexico": 0.0268, "Belgium": 0.0261, "Switzerland": 0.0133, "USA": 0.0123, "Croatia": 0.0073}}, {"ts": "2026-06-28T04:34:46Z", "label": "Live", "probs": {"Argentina": 0.2188, "France": 0.1425, "Spain": 0.109, "England": 0.0783, "Brazil": 0.0718, "Portugal": 0.0622, "Colombia": 0.0515, "Netherlands": 0.0476, "Germany": 0.036, "Morocco": 0.0305, "Belgium": 0.0286, "Mexico": 0.0269, "Japan": 0.0256, "Switzerland": 0.0142, "USA": 0.0123, "Norway": 0.0076}}, {"ts": "2026-06-28T05:10:40Z", "label": "Live", "probs": {"Argentina": 0.2196, "France": 0.1431, "Spain": 0.1086, "England": 0.0759, "Brazil": 0.0729, "Colombia": 0.0579, "Portugal": 0.0518, "Netherlands": 0.0463, "Germany": 0.0363, "Morocco": 0.0312, "Japan": 0.027, "Mexico": 0.0269, "Belgium": 0.0261, "Switzerland": 0.0132, "USA": 0.0123, "Croatia": 0.0073}}, {"ts": "2026-06-29T19:44:14Z", "label": "Live", "probs": {"Argentina": 0.2136, "France": 0.1418, "Brazil": 0.1347, "Spain": 0.105, "England": 0.071, "Colombia": 0.0545, "Portugal": 0.0498, "Netherlands": 0.0408, "Germany": 0.0351, "Morocco": 0.0279, "Belgium": 0.0255, "Mexico": 0.0246, "Switzerland": 0.0126, "USA": 0.0118, "Canada": 0.0089, "Croatia": 0.0069}}, {"ts": "2026-06-29T19:48:17Z", "label": "Live", "probs": {"Argentina": 0.2136, "France": 0.1418, "Brazil": 0.1346, "Spain": 0.1051, "England": 0.071, "Colombia": 0.0544, "Portugal": 0.0498, "Netherlands": 0.0407, "Germany": 0.0352, "Morocco": 0.028, "Belgium": 0.0255, "Mexico": 0.0246, "Switzerland": 0.0126, "USA": 0.0118, "Canada": 0.0089, "Croatia": 0.0069}}, {"ts": "2026-07-02T21:01:23Z", "label": "Live", "probs": {"France": 0.2035, "Argentina": 0.2027, "Brazil": 0.1175, "Spain": 0.0938, "England": 0.083, "Morocco": 0.0666, "Colombia": 0.0494, "Portugal": 0.0431, "Mexico": 0.0395, "Belgium": 0.0364, "USA": 0.016, "Switzerland": 0.0102, "Norway": 0.0096, "Canada": 0.0075, "Croatia": 0.0061, "Australia": 0.0044}}, {"ts": "2026-07-02T21:10:47Z", "label": "Live", "probs": {"France": 0.1956, "Argentina": 0.1938, "Spain": 0.1379, "Brazil": 0.115, "England": 0.0826, "Morocco": 0.0621, "Colombia": 0.0481, "Mexico": 0.0373, "Portugal": 0.0356, "Belgium": 0.0338, "USA": 0.0135, "Switzerland": 0.0105, "Norway": 0.0099, "Canada": 0.0075, "Australia": 0.0045, "Croatia": 0.004}}, {"ts": "2026-07-06T22:31:30Z", "label": "Live", "probs": {"Spain": 0.2421, "Argentina": 0.1927, "England": 0.184, "France": 0.1735, "Morocco": 0.0856, "Colombia": 0.0439, "Norway": 0.0326, "Belgium": 0.0211, "Switzerland": 0.0145, "USA": 0.007, "Egypt": 0.0029, "Mexico": 0.0, "South Africa": 0.0, "South Korea": 0.0, "Czech Republic": 0.0, "Canada": 0.0}}, {"ts": "2026-07-06T22:32:52Z", "label": "Live", "probs": {"Spain": 0.242, "Argentina": 0.1927, "England": 0.1842, "France": 0.1733, "Morocco": 0.0856, "Colombia": 0.044, "Norway": 0.0326, "Belgium": 0.0211, "Switzerland": 0.0145, "USA": 0.0071, "Egypt": 0.0029, "Mexico": 0.0, "South Africa": 0.0, "South Korea": 0.0, "Czech Republic": 0.0, "Canada": 0.0}}, {"ts": "2026-07-06T22:33:56Z", "label": "Live", "probs": {"Spain": 0.2316, "Argentina": 0.2065, "France": 0.1794, "England": 0.1657, "Morocco": 0.0847, "Colombia": 0.0506, "Norway": 0.036, "Belgium": 0.0212, "Switzerland": 0.0134, "USA": 0.0078, "Egypt": 0.0031, "Mexico": 0.0, "South Africa": 0.0, "South Korea": 0.0, "Czech Republic": 0.0, "Canada": 0.0}}, {"ts": "2026-07-09T05:14:59Z", "label": "Live", "probs": {"Spain": 0.2329, "France": 0.1923, "Argentina": 0.184, "England": 0.1633, "Morocco": 0.0895, "Switzerland": 0.051, "Belgium": 0.048, "Norway": 0.039, "Mexico": 0.0, "South Africa": 0.0, "South Korea": 0.0, "Czech Republic": 0.0, "Canada": 0.0, "Bosnia-Herzegovina": 0.0, "Qatar": 0.0, "Brazil": 0.0}}, {"ts": "2026-07-09T08:57:37Z", "label": "Live", "probs": {"Spain": 0.2329, "France": 0.1922, "Argentina": 0.184, "England": 0.1633, "Morocco": 0.0896, "Switzerland": 0.0509, "Belgium": 0.048, "Norway": 0.039, "Mexico": 0.0, "South Africa": 0.0, "South Korea": 0.0, "Czech Republic": 0.0, "Canada": 0.0, "Bosnia-Herzegovina": 0.0, "Qatar": 0.0, "Brazil": 0.0}}, {"ts": "2026-07-09T13:33:34Z", "label": "Live", "probs": {"Spain": 0.233, "France": 0.1923, "Argentina": 0.1839, "England": 0.1633, "Morocco": 0.0895, "Switzerland": 0.0509, "Belgium": 0.048, "Norway": 0.0391, "Mexico": 0.0, "South Africa": 0.0, "South Korea": 0.0, "Czech Republic": 0.0, "Canada": 0.0, "Bosnia-Herzegovina": 0.0, "Qatar": 0.0, "Brazil": 0.0}}, {"ts": "2026-07-09T15:39:32Z", "label": "Live", "probs": {"Spain": 0.2329, "France": 0.1922, "Argentina": 0.1841, "England": 0.1633, "Morocco": 0.0895, "Switzerland": 0.0509, "Belgium": 0.048, "Norway": 0.0391, "Mexico": 0.0, "South Africa": 0.0, "South Korea": 0.0, "Czech Republic": 0.0, "Canada": 0.0, "Bosnia-Herzegovina": 0.0, "Qatar": 0.0, "Brazil": 0.0}}, {"ts": "2026-07-09T18:15:09Z", "label": "Live", "probs": {"Spain": 0.2329, "France": 0.1922, "Argentina": 0.1841, "England": 0.1633, "Morocco": 0.0894, "Switzerland": 0.0509, "Belgium": 0.048, "Norway": 0.0391, "Mexico": 0.0, "South Africa": 0.0, "South Korea": 0.0, "Czech Republic": 0.0, "Canada": 0.0, "Bosnia-Herzegovina": 0.0, "Qatar": 0.0, "Brazil": 0.0}}, {"ts": "2026-07-09T20:13:25Z", "label": "Live", "probs": {"Spain": 0.233, "France": 0.1921, "Argentina": 0.1842, "England": 0.1633, "Morocco": 0.0895, "Switzerland": 0.0509, "Belgium": 0.048, "Norway": 0.0391, "Mexico": 0.0, "South Africa": 0.0, "South Korea": 0.0, "Czech Republic": 0.0, "Canada": 0.0, "Bosnia-Herzegovina": 0.0, "Qatar": 0.0, "Brazil": 0.0}}, {"ts": "2026-07-09T21:53:12Z", "label": "Live", "probs": {"Spain": 0.2331, "France": 0.1919, "Argentina": 0.1842, "England": 0.1633, "Morocco": 0.0895, "Switzerland": 0.0509, "Belgium": 0.048, "Norway": 0.0391, "Mexico": 0.0, "South Africa": 0.0, "South Korea": 0.0, "Czech Republic": 0.0, "Canada": 0.0, "Bosnia-Herzegovina": 0.0, "Qatar": 0.0, "Brazil": 0.0}}, {"ts": "2026-07-09T23:41:19Z", "label": "Live", "probs": {"France": 0.3714, "Spain": 0.1976, "Argentina": 0.1674, "England": 0.1446, "Switzerland": 0.0443, "Belgium": 0.0386, "Norway": 0.036, "Mexico": 0.0, "South Africa": 0.0, "South Korea": 0.0, "Czech Republic": 0.0, "Canada": 0.0, "Bosnia-Herzegovina": 0.0, "Qatar": 0.0, "Brazil": 0.0, "Morocco": 0.0}}, {"ts": "2026-07-10T04:29:42Z", "label": "Live", "probs": {"France": 0.3714, "Spain": 0.1975, "Argentina": 0.1674, "England": 0.1447, "Switzerland": 0.0444, "Belgium": 0.0386, "Norway": 0.036, "Mexico": 0.0, "South Africa": 0.0, "South Korea": 0.0, "Czech Republic": 0.0, "Canada": 0.0, "Bosnia-Herzegovina": 0.0, "Qatar": 0.0, "Brazil": 0.0, "Morocco": 0.0}}, {"ts": "2026-07-10T08:46:22Z", "label": "Live", "probs": {"France": 0.3715, "Spain": 0.1974, "Argentina": 0.1675, "England": 0.1447, "Switzerland": 0.0444, "Belgium": 0.0386, "Norway": 0.0359, "Mexico": 0.0, "South Africa": 0.0, "South Korea": 0.0, "Czech Republic": 0.0, "Canada": 0.0, "Bosnia-Herzegovina": 0.0, "Qatar": 0.0, "Brazil": 0.0, "Morocco": 0.0}}, {"ts": "2026-07-10T12:11:21Z", "label": "Live", "probs": {"France": 0.3715, "Spain": 0.1974, "Argentina": 0.1675, "England": 0.1447, "Switzerland": 0.0445, "Belgium": 0.0386, "Norway": 0.0359, "Mexico": 0.0, "South Africa": 0.0, "South Korea": 0.0, "Czech Republic": 0.0, "Canada": 0.0, "Bosnia-Herzegovina": 0.0, "Qatar": 0.0, "Brazil": 0.0, "Morocco": 0.0}}, {"ts": "2026-07-10T15:07:11Z", "label": "Live", "probs": {"France": 0.3714, "Spain": 0.1976, "Argentina": 0.1673, "England": 0.1447, "Switzerland": 0.0445, "Belgium": 0.0386, "Norway": 0.0359, "Mexico": 0.0, "South Africa": 0.0, "South Korea": 0.0, "Czech Republic": 0.0, "Canada": 0.0, "Bosnia-Herzegovina": 0.0, "Qatar": 0.0, "Brazil": 0.0, "Morocco": 0.0}}, {"ts": "2026-07-10T17:14:25Z", "label": "Live", "probs": {"France": 0.3716, "Spain": 0.1975, "Argentina": 0.1673, "England": 0.1447, "Switzerland": 0.0444, "Belgium": 0.0386, "Norway": 0.0359, "Mexico": 0.0, "South Africa": 0.0, "South Korea": 0.0, "Czech Republic": 0.0, "Canada": 0.0, "Bosnia-Herzegovina": 0.0, "Qatar": 0.0, "Brazil": 0.0, "Morocco": 0.0}}, {"ts": "2026-07-10T18:53:50Z", "label": "Live", "probs": {"France": 0.3715, "Spain": 0.1975, "Argentina": 0.1673, "England": 0.1447, "Switzerland": 0.0444, "Belgium": 0.0386, "Norway": 0.0359, "Mexico": 0.0, "South Africa": 0.0, "South Korea": 0.0, "Czech Republic": 0.0, "Canada": 0.0, "Bosnia-Herzegovina": 0.0, "Qatar": 0.0, "Brazil": 0.0, "Morocco": 0.0}}, {"ts": "2026-07-10T20:46:31Z", "label": "Live", "probs": {"France": 0.3716, "Spain": 0.1975, "Argentina": 0.1673, "England": 0.1447, "Switzerland": 0.0445, "Belgium": 0.0386, "Norway": 0.0359, "Mexico": 0.0, "South Africa": 0.0, "South Korea": 0.0, "Czech Republic": 0.0, "Canada": 0.0, "Bosnia-Herzegovina": 0.0, "Qatar": 0.0, "Brazil": 0.0, "Morocco": 0.0}}, {"ts": "2026-07-10T22:23:45Z", "label": "Live", "probs": {"France": 0.3287, "Spain": 0.2992, "Argentina": 0.1589, "England": 0.1377, "Switzerland": 0.0408, "Norway": 0.0347, "Mexico": 0.0, "South Africa": 0.0, "South Korea": 0.0, "Czech Republic": 0.0, "Canada": 0.0, "Bosnia-Herzegovina": 0.0, "Qatar": 0.0, "Brazil": 0.0, "Morocco": 0.0, "Haiti": 0.0}}, {"ts": "2026-07-10T22:29:36Z", "label": "Live", "probs": {"France": 0.3287, "Spain": 0.2992, "Argentina": 0.1589, "England": 0.1377, "Switzerland": 0.0408, "Norway": 0.0347, "Mexico": 0.0, "South Africa": 0.0, "South Korea": 0.0, "Czech Republic": 0.0, "Canada": 0.0, "Bosnia-Herzegovina": 0.0, "Qatar": 0.0, "Brazil": 0.0, "Morocco": 0.0, "Haiti": 0.0}}, {"ts": "2026-07-11T00:14:59Z", "label": "Live", "probs": {"France": 0.3287, "Spain": 0.2992, "Argentina": 0.1589, "England": 0.1376, "Switzerland": 0.0408, "Norway": 0.0347, "Mexico": 0.0, "South Africa": 0.0, "South Korea": 0.0, "Czech Republic": 0.0, "Canada": 0.0, "Bosnia-Herzegovina": 0.0, "Qatar": 0.0, "Brazil": 0.0, "Morocco": 0.0, "Haiti": 0.0}}, {"ts": "2026-07-11T03:48:57Z", "label": "Live", "probs": {"France": 0.3286, "Spain": 0.2994, "Argentina": 0.1589, "England": 0.1377, "Switzerland": 0.0408, "Norway": 0.0346, "Mexico": 0.0, "South Africa": 0.0, "South Korea": 0.0, "Czech Republic": 0.0, "Canada": 0.0, "Bosnia-Herzegovina": 0.0, "Qatar": 0.0, "Brazil": 0.0, "Morocco": 0.0, "Haiti": 0.0}}, {"ts": "2026-07-11T06:31:07Z", "label": "Live", "probs": {"France": 0.3286, "Spain": 0.2994, "Argentina": 0.1589, "England": 0.1377, "Switzerland": 0.0408, "Norway": 0.0346, "Mexico": 0.0, "South Africa": 0.0, "South Korea": 0.0, "Czech Republic": 0.0, "Canada": 0.0, "Bosnia-Herzegovina": 0.0, "Qatar": 0.0, "Brazil": 0.0, "Morocco": 0.0, "Haiti": 0.0}}]}