{"snapshots": [{"ts": "2026-06-26T11:47:45Z", "label": "Live", "probs": {"Argentina": 0.1957, "France": 0.166, "Spain": 0.1252, "England": 0.1129, "Brazil": 0.0894, "Portugal": 0.0735, "Germany": 0.0558, "Netherlands": 0.0473, "Colombia": 0.0409, "Belgium": 0.0238, "USA": 0.0175, "Japan": 0.0137, "Uruguay": 0.0093, "Morocco": 0.0073, "Croatia": 0.0055, "Mexico": 0.0051}}, {"ts": "2026-06-26T14:35:34Z", "label": "Live", "probs": {"Argentina": 0.1957, "France": 0.166, "Spain": 0.1252, "England": 0.1129, "Brazil": 0.0894, "Portugal": 0.0735, "Germany": 0.0558, "Netherlands": 0.0473, "Colombia": 0.0409, "Belgium": 0.0238, "USA": 0.0175, "Japan": 0.0137, "Uruguay": 0.0093, "Morocco": 0.0073, "Croatia": 0.0055, "Mexico": 0.0051}}, {"ts": "2026-06-26T17:04:04Z", "label": "Live", "probs": {"Argentina": 0.1957, "France": 0.166, "Spain": 0.1252, "England": 0.1129, "Brazil": 0.0894, "Portugal": 0.0735, "Germany": 0.0558, "Netherlands": 0.0473, "Colombia": 0.0409, "Belgium": 0.0238, "USA": 0.0175, "Japan": 0.0137, "Uruguay": 0.0093, "Morocco": 0.0073, "Croatia": 0.0055, "Mexico": 0.0051}}, {"ts": "2026-06-26T17:40:34Z", "label": "Live", "probs": {"Argentina": 0.1957, "France": 0.166, "Spain": 0.1252, "England": 0.1129, "Brazil": 0.0894, "Portugal": 0.0735, "Germany": 0.0558, "Netherlands": 0.0473, "Colombia": 0.0409, "Belgium": 0.0238, "USA": 0.0175, "Japan": 0.0137, "Uruguay": 0.0093, "Morocco": 0.0073, "Croatia": 0.0055, "Mexico": 0.0051}}, {"ts": "2026-06-26T17:42:54Z", "label": "Live", "probs": {"Argentina": 0.1957, "France": 0.166, "Spain": 0.1252, "England": 0.1129, "Brazil": 0.0894, "Portugal": 0.0735, "Germany": 0.0558, "Netherlands": 0.0473, "Colombia": 0.0409, "Belgium": 0.0238, "USA": 0.0175, "Japan": 0.0137, "Uruguay": 0.0093, "Morocco": 0.0073, "Croatia": 0.0055, "Mexico": 0.0051}}, {"ts": "2026-06-26T17:44:45Z", "label": "Live", "probs": {"Argentina": 0.1957, "France": 0.166, "Spain": 0.1252, "England": 0.1129, "Brazil": 0.0894, "Portugal": 0.0735, "Germany": 0.0558, "Netherlands": 0.0473, "Colombia": 0.0409, "Belgium": 0.0238, "USA": 0.0175, "Japan": 0.0137, "Uruguay": 0.0093, "Morocco": 0.0073, "Croatia": 0.0055, "Mexico": 0.0051}}, {"ts": "2026-06-26T17:58:07Z", "label": "Live", "probs": {"Argentina": 0.1957, "France": 0.166, "Spain": 0.1252, "England": 0.1129, "Brazil": 0.0894, "Portugal": 0.0735, "Germany": 0.0558, "Netherlands": 0.0473, "Colombia": 0.0409, "Belgium": 0.0238, "USA": 0.0175, "Japan": 0.0137, "Uruguay": 0.0093, "Morocco": 0.0073, "Croatia": 0.0055, "Mexico": 0.0051}}, {"ts": "2026-06-26T18:26:49Z", "label": "Live", "probs": {"Argentina": 0.1957, "France": 0.166, "Spain": 0.1252, "England": 0.1129, "Brazil": 0.0894, "Portugal": 0.0735, "Germany": 0.0558, "Netherlands": 0.0473, "Colombia": 0.0409, "Belgium": 0.0238, "USA": 0.0175, "Japan": 0.0137, "Uruguay": 0.0093, "Morocco": 0.0073, "Croatia": 0.0055, "Mexico": 0.0051}}, {"ts": "2026-06-26T18:28:39Z", "label": "Live", "probs": {"Argentina": 0.1957, "France": 0.166, "Spain": 0.1252, "England": 0.1129, "Brazil": 0.0894, "Portugal": 0.0735, "Germany": 0.0558, "Netherlands": 0.0473, "Colombia": 0.0409, "Belgium": 0.0238, "USA": 0.0175, "Japan": 0.0137, "Uruguay": 0.0093, "Morocco": 0.0073, "Croatia": 0.0055, "Mexico": 0.0051}}, {"ts": "2026-06-26T19:12:05Z", "label": "Live", "probs": {"Argentina": 0.1957, "France": 0.166, "Spain": 0.1252, "England": 0.1129, "Brazil": 0.0894, "Portugal": 0.0735, "Germany": 0.0558, "Netherlands": 0.0473, "Colombia": 0.0409, "Belgium": 0.0238, "USA": 0.0175, "Japan": 0.0137, "Uruguay": 0.0093, "Morocco": 0.0073, "Croatia": 0.0055, "Mexico": 0.0051}}, {"ts": "2026-06-26T19:13:05Z", "label": "Live", "probs": {"Argentina": 0.1957, "France": 0.166, "Spain": 0.1252, "England": 0.1129, "Brazil": 0.0894, "Portugal": 0.0735, "Germany": 0.0558, "Netherlands": 0.0473, "Colombia": 0.0409, "Belgium": 0.0238, "USA": 0.0175, "Japan": 0.0137, "Uruguay": 0.0093, "Morocco": 0.0073, "Croatia": 0.0055, "Mexico": 0.0051}}, {"ts": "2026-06-26T19:35:39Z", "label": "Live", "probs": {"Argentina": 0.1957, "France": 0.166, "Spain": 0.1252, "England": 0.1129, "Brazil": 0.0894, "Portugal": 0.0735, "Germany": 0.0558, "Netherlands": 0.0473, "Colombia": 0.0409, "Belgium": 0.0238, "USA": 0.0175, "Japan": 0.0137, "Uruguay": 0.0093, "Morocco": 0.0073, "Croatia": 0.0055, "Mexico": 0.0051}}, {"ts": "2026-06-26T19:42:20Z", "label": "Live", "probs": {"Argentina": 0.1957, "France": 0.166, "Spain": 0.1252, "England": 0.1129, "Brazil": 0.0894, "Portugal": 0.0735, "Germany": 0.0558, "Netherlands": 0.0473, "Colombia": 0.0409, "Belgium": 0.0238, "USA": 0.0175, "Japan": 0.0137, "Uruguay": 0.0093, "Morocco": 0.0073, "Croatia": 0.0055, "Mexico": 0.0051}}, {"ts": "2026-06-26T19:57:36Z", "label": "Live", "probs": {"Argentina": 0.1957, "France": 0.166, "Spain": 0.1252, "England": 0.1129, "Brazil": 0.0894, "Portugal": 0.0735, "Germany": 0.0558, "Netherlands": 0.0473, "Colombia": 0.0409, "Belgium": 0.0238, "USA": 0.0175, "Japan": 0.0137, "Uruguay": 0.0093, "Morocco": 0.0073, "Croatia": 0.0055, "Mexico": 0.0051}}, {"ts": "2026-06-26T21:25:30Z", "label": "Live", "probs": {"Argentina": 0.1956, "France": 0.1573, "Spain": 0.1272, "England": 0.1197, "Brazil": 0.0939, "Portugal": 0.0706, "Germany": 0.0586, "Netherlands": 0.0449, "Colombia": 0.0411, "Belgium": 0.0258, "USA": 0.0182, "Japan": 0.0121, "Morocco": 0.0077, "Uruguay": 0.0075, "Mexico": 0.0043, "Ecuador": 0.0036}}, {"ts": "2026-06-26T23:12:38Z", "label": "Live", "probs": {"Argentina": 0.1956, "France": 0.1573, "Spain": 0.1272, "England": 0.1197, "Brazil": 0.0939, "Portugal": 0.0706, "Germany": 0.0586, "Netherlands": 0.0449, "Colombia": 0.0411, "Belgium": 0.0258, "USA": 0.0182, "Japan": 0.0121, "Morocco": 0.0077, "Uruguay": 0.0075, "Mexico": 0.0043, "Ecuador": 0.0036}}, {"ts": "2026-06-26T23:50:40Z", "label": "Live", "probs": {"Argentina": 0.2002, "France": 0.1601, "Spain": 0.1298, "England": 0.1173, "Brazil": 0.0897, "Portugal": 0.0679, "Germany": 0.0554, "Netherlands": 0.0472, "Colombia": 0.0364, "Belgium": 0.0243, "USA": 0.0194, "Japan": 0.013, "Morocco": 0.0097, "Uruguay": 0.0084, "Croatia": 0.0053, "Mexico": 0.0047}}, {"ts": "2026-06-27T00:06:37Z", "label": "Live", "probs": {"Argentina": 0.2002, "France": 0.1601, "Spain": 0.1298, "England": 0.1173, "Brazil": 0.0897, "Portugal": 0.0679, "Germany": 0.0554, "Netherlands": 0.0472, "Colombia": 0.0364, "Belgium": 0.0243, "USA": 0.0194, "Japan": 0.013, "Morocco": 0.0097, "Uruguay": 0.0084, "Croatia": 0.0053, "Mexico": 0.0047}}, {"ts": "2026-06-27T02:15:19Z", "label": "Live", "probs": {"Argentina": 0.2136, "France": 0.1526, "Spain": 0.1361, "England": 0.11, "Brazil": 0.0928, "Portugal": 0.0689, "Germany": 0.0549, "Netherlands": 0.0438, "Colombia": 0.0375, "Belgium": 0.0251, "USA": 0.0185, "Japan": 0.0146, "Morocco": 0.0089, "Mexico": 0.0055, "Croatia": 0.0051, "Switzerland": 0.0034}}, {"ts": "2026-06-27T03:55:37Z", "label": "Live", "probs": {"Argentina": 0.2136, "France": 0.1526, "Spain": 0.1361, "England": 0.11, "Brazil": 0.0928, "Portugal": 0.0689, "Germany": 0.0549, "Netherlands": 0.0438, "Colombia": 0.0375, "Belgium": 0.0251, "USA": 0.0185, "Japan": 0.0146, "Morocco": 0.0089, "Mexico": 0.0055, "Croatia": 0.0051, "Switzerland": 0.0034}}, {"ts": "2026-06-27T06:57:42Z", "label": "Live", "probs": {"Argentina": 0.2404, "France": 0.1442, "Spain": 0.1264, "England": 0.1163, "Brazil": 0.0885, "Portugal": 0.0657, "Germany": 0.0557, "Netherlands": 0.0432, "Colombia": 0.0385, "Belgium": 0.0259, "USA": 0.0135, "Japan": 0.013, "Morocco": 0.0074, "Croatia": 0.0057, "Switzerland": 0.0046, "Mexico": 0.0033}}, {"ts": "2026-06-27T09:33:19Z", "label": "Live", "probs": {"Argentina": 0.2404, "France": 0.1442, "Spain": 0.1264, "England": 0.1163, "Brazil": 0.0885, "Portugal": 0.0657, "Germany": 0.0557, "Netherlands": 0.0432, "Colombia": 0.0385, "Belgium": 0.0259, "USA": 0.0135, "Japan": 0.013, "Morocco": 0.0074, "Croatia": 0.0057, "Switzerland": 0.0046, "Mexico": 0.0033}}, {"ts": "2026-06-27T11:17:19Z", "label": "Live", "probs": {"Argentina": 0.2384, "France": 0.1517, "Spain": 0.1269, "England": 0.1114, "Brazil": 0.0871, "Portugal": 0.0671, "Germany": 0.0534, "Netherlands": 0.0436, "Colombia": 0.0393, "Belgium": 0.0273, "USA": 0.0134, "Japan": 0.013, "Morocco": 0.0072, "Switzerland": 0.0047, "Croatia": 0.0043, "Mexico": 0.0041}}, {"ts": "2026-06-27T11:40:50Z", "label": "Live", "probs": {"Argentina": 0.2384, "France": 0.1517, "Spain": 0.1269, "England": 0.1114, "Brazil": 0.0871, "Portugal": 0.0671, "Germany": 0.0534, "Netherlands": 0.0436, "Colombia": 0.0393, "Belgium": 0.0273, "USA": 0.0134, "Japan": 0.013, "Morocco": 0.0072, "Switzerland": 0.0047, "Croatia": 0.0043, "Mexico": 0.0041}}, {"ts": "2026-06-27T11:50:22Z", "label": "Live", "probs": {"Argentina": 0.2384, "France": 0.1517, "Spain": 0.1269, "England": 0.1114, "Brazil": 0.0871, "Portugal": 0.0671, "Germany": 0.0534, "Netherlands": 0.0436, "Colombia": 0.0393, "Belgium": 0.0273, "USA": 0.0134, "Japan": 0.013, "Morocco": 0.0072, "Switzerland": 0.0047, "Croatia": 0.0043, "Mexico": 0.0041}}, {"ts": "2026-06-27T13:54:35Z", "label": "Live", "probs": {"Argentina": 0.2384, "France": 0.1517, "Spain": 0.1269, "England": 0.1114, "Brazil": 0.0871, "Portugal": 0.0671, "Germany": 0.0534, "Netherlands": 0.0436, "Colombia": 0.0393, "Belgium": 0.0273, "USA": 0.0134, "Japan": 0.013, "Morocco": 0.0072, "Switzerland": 0.0047, "Croatia": 0.0043, "Mexico": 0.0041}}, {"ts": "2026-06-27T15:21:22Z", "label": "Live", "probs": {"Argentina": 0.2384, "France": 0.1517, "Spain": 0.1269, "England": 0.1114, "Brazil": 0.0871, "Portugal": 0.0671, "Germany": 0.0534, "Netherlands": 0.0436, "Colombia": 0.0393, "Belgium": 0.0273, "USA": 0.0134, "Japan": 0.013, "Morocco": 0.0072, "Switzerland": 0.0047, "Croatia": 0.0043, "Mexico": 0.0041}}, {"ts": "2026-06-27T17:18:30Z", "label": "Live", "probs": {"Argentina": 0.2384, "France": 0.1517, "Spain": 0.1269, "England": 0.1114, "Brazil": 0.0871, "Portugal": 0.0671, "Germany": 0.0534, "Netherlands": 0.0436, "Colombia": 0.0393, "Belgium": 0.0273, "USA": 0.0134, "Japan": 0.013, "Morocco": 0.0072, "Switzerland": 0.0047, "Croatia": 0.0043, "Mexico": 0.0041}}, {"ts": "2026-06-27T19:37:50Z", "label": "Live", "probs": {"Argentina": 0.2384, "France": 0.1517, "Spain": 0.1269, "England": 0.1114, "Brazil": 0.0871, "Portugal": 0.0671, "Germany": 0.0534, "Netherlands": 0.0436, "Colombia": 0.0393, "Belgium": 0.0273, "USA": 0.0134, "Japan": 0.013, "Morocco": 0.0072, "Switzerland": 0.0047, "Croatia": 0.0043, "Mexico": 0.0041}}, {"ts": "2026-06-27T19:51:02Z", "label": "Live", "probs": {"Argentina": 0.1457, "France": 0.1336, "Spain": 0.112, "Brazil": 0.0819, "Mexico": 0.0773, "Colombia": 0.0467, "Netherlands": 0.0405, "Portugal": 0.0383, "Germany": 0.0376, "England": 0.0345, "Belgium": 0.0339, "Morocco": 0.0311, "Japan": 0.03, "USA": 0.0265, "Switzerland": 0.0263, "Canada": 0.0171}}]}