{"teams": [{"team": "France", "confederation": "UEFA", "color": "#58a6ff", "fifa_rank": 2, "p_r32": 1.0, "p_r16": 1.0, "p_qf": 0.811, "p_sf": 0.57, "p_final": 0.3577, "p_win": 0.2185, "eliminated": false}, {"team": "Argentina", "confederation": "CONMEBOL", "color": "#3fb950", "fifa_rank": 1, "p_r32": 1.0, "p_r16": 0.7938, "p_qf": 0.6102, "p_sf": 0.4156, "p_final": 0.249, "p_win": 0.1399, "eliminated": false}, {"team": "Spain", "confederation": "UEFA", "color": "#58a6ff", "fifa_rank": 3, "p_r32": 1.0, "p_r16": 1.0, "p_qf": 0.6065, "p_sf": 0.4192, "p_final": 0.2349, "p_win": 0.1367, "eliminated": false}, {"team": "Brazil", "confederation": "CONMEBOL", "color": "#3fb950", "fifa_rank": 5, "p_r32": 1.0, "p_r16": 1.0, "p_qf": 0.7585, "p_sf": 0.4275, "p_final": 0.2469, "p_win": 0.1272, "eliminated": false}, {"team": "England", "confederation": "UEFA", "color": "#58a6ff", "fifa_rank": 4, "p_r32": 1.0, "p_r16": 1.0, "p_qf": 0.5081, "p_sf": 0.2536, "p_final": 0.132, "p_win": 0.0609, "eliminated": false}, {"team": "Mexico", "confederation": "CONCACAF", "color": "#f97316", "fifa_rank": 16, "p_r32": 1.0, "p_r16": 1.0, "p_qf": 0.4919, "p_sf": 0.2485, "p_final": 0.1306, "p_win": 0.0595, "eliminated": false}, {"team": "Morocco", "confederation": "CAF", "color": "#d29922", "fifa_rank": 14, "p_r32": 1.0, "p_r16": 1.0, "p_qf": 0.6275, "p_sf": 0.2513, "p_final": 0.1146, "p_win": 0.0508, "eliminated": false}, {"team": "Portugal", "confederation": "UEFA", "color": "#58a6ff", "fifa_rank": 6, "p_r32": 1.0, "p_r16": 1.0, "p_qf": 0.3935, "p_sf": 0.2273, "p_final": 0.1033, "p_win": 0.0495, "eliminated": false}, {"team": "Colombia", "confederation": "CONMEBOL", "color": "#3fb950", "fifa_rank": 9, "p_r32": 1.0, "p_r16": 0.7266, "p_qf": 0.4102, "p_sf": 0.2009, "p_final": 0.0893, "p_win": 0.0371, "eliminated": false}, {"team": "Switzerland", "confederation": "UEFA", "color": "#58a6ff", "fifa_rank": 18, "p_r32": 1.0, "p_r16": 1.0, "p_qf": 0.5167, "p_sf": 0.2353, "p_final": 0.0903, "p_win": 0.0326, "eliminated": false}, {"team": "Belgium", "confederation": "UEFA", "color": "#58a6ff", "fifa_rank": 10, "p_r32": 1.0, "p_r16": 1.0, "p_qf": 0.5045, "p_sf": 0.1793, "p_final": 0.068, "p_win": 0.0271, "eliminated": false}, {"team": "USA", "confederation": "CONCACAF", "color": "#f97316", "fifa_rank": 13, "p_r32": 1.0, "p_r16": 1.0, "p_qf": 0.4955, "p_sf": 0.1742, "p_final": 0.066, "p_win": 0.0267, "eliminated": false}, {"team": "Canada", "confederation": "CONCACAF", "color": "#f97316", "fifa_rank": 22, "p_r32": 1.0, "p_r16": 1.0, "p_qf": 0.3725, "p_sf": 0.1257, "p_final": 0.0424, "p_win": 0.015, "eliminated": false}, {"team": "Norway", "confederation": "UEFA", "color": "#58a6ff", "fifa_rank": 23, "p_r32": 1.0, "p_r16": 1.0, "p_qf": 0.2415, "p_sf": 0.0704, "p_final": 0.0243, "p_win": 0.0065, "eliminated": false}, {"team": "Australia", "confederation": "AFC", "color": "#bc8cff", "fifa_rank": 25, "p_r32": 1.0, "p_r16": 0.5519, "p_qf": 0.1762, "p_sf": 0.0617, "p_final": 0.0162, "p_win": 0.0041, "eliminated": false}, {"team": "Paraguay", "confederation": "CONMEBOL", "color": "#3fb950", "fifa_rank": 38, "p_r32": 1.0, "p_r16": 1.0, "p_qf": 0.189, "p_sf": 0.0531, "p_final": 0.0131, "p_win": 0.003, "eliminated": false}, {"team": "Egypt", "confederation": "CAF", "color": "#d29922", "fifa_rank": 32, "p_r32": 1.0, "p_r16": 0.4481, "p_qf": 0.1407, "p_sf": 0.0454, "p_final": 0.0119, "p_win": 0.0028, "eliminated": false}, {"team": "Ghana", "confederation": "CAF", "color": "#d29922", "fifa_rank": 37, "p_r32": 1.0, "p_r16": 0.2735, "p_qf": 0.0731, "p_sf": 0.0218, "p_final": 0.0055, "p_win": 0.0013, "eliminated": false}, {"team": "Cape Verde", "confederation": "CAF", "color": "#d29922", "fifa_rank": 43, "p_r32": 1.0, "p_r16": 0.2062, "p_qf": 0.0728, "p_sf": 0.0193, "p_final": 0.0042, "p_win": 0.0009, "eliminated": false}, {"team": "South Africa", "confederation": "CAF", "color": "#d29922", "fifa_rank": 31, "p_r32": 1.0, "p_r16": 0.0, "p_qf": 0.0, "p_sf": 0.0, "p_final": 0.0, "p_win": 0.0, "eliminated": true}, {"team": "South Korea", "confederation": "AFC", "color": "#bc8cff", "fifa_rank": 19, "p_r32": 0.0, "p_r16": 0.0, "p_qf": 0.0, "p_sf": 0.0, "p_final": 0.0, "p_win": 0.0, "eliminated": true}, {"team": "Czech Republic", "confederation": "UEFA", "color": "#58a6ff", "fifa_rank": 30, "p_r32": 0.0, "p_r16": 0.0, "p_qf": 0.0, "p_sf": 0.0, "p_final": 0.0, "p_win": 0.0, "eliminated": true}, {"team": "Bosnia-Herzegovina", "confederation": "UEFA", "color": "#58a6ff", "fifa_rank": 29, "p_r32": 1.0, "p_r16": 0.0, "p_qf": 0.0, "p_sf": 0.0, "p_final": 0.0, "p_win": 0.0, "eliminated": true}, {"team": "Qatar", "confederation": "AFC", "color": "#bc8cff", "fifa_rank": 45, "p_r32": 0.0, "p_r16": 0.0, "p_qf": 0.0, "p_sf": 0.0, "p_final": 0.0, "p_win": 0.0, "eliminated": true}, {"team": "Haiti", "confederation": "CONCACAF", "color": "#f97316", "fifa_rank": 48, "p_r32": 0.0, "p_r16": 0.0, "p_qf": 0.0, "p_sf": 0.0, "p_final": 0.0, "p_win": 0.0, "eliminated": true}, {"team": "Scotland", "confederation": "UEFA", "color": "#58a6ff", "fifa_rank": 28, "p_r32": 0.0, "p_r16": 0.0, "p_qf": 0.0, "p_sf": 0.0, "p_final": 0.0, "p_win": 0.0, "eliminated": true}, {"team": "Turkey", "confederation": "UEFA", "color": "#58a6ff", "fifa_rank": 20, "p_r32": 0.0, "p_r16": 0.0, "p_qf": 0.0, "p_sf": 0.0, "p_final": 0.0, "p_win": 0.0, "eliminated": true}, {"team": "Germany", "confederation": "UEFA", "color": "#58a6ff", "fifa_rank": 7, "p_r32": 1.0, "p_r16": 0.0, "p_qf": 0.0, "p_sf": 0.0, "p_final": 0.0, "p_win": 0.0, "eliminated": true}, {"team": "Curacao", "confederation": "CONCACAF", "color": "#f97316", "fifa_rank": 47, "p_r32": 0.0, "p_r16": 0.0, "p_qf": 0.0, "p_sf": 0.0, "p_final": 0.0, "p_win": 0.0, "eliminated": true}, {"team": "Ivory Coast", "confederation": "CAF", "color": "#d29922", "fifa_rank": 33, "p_r32": 1.0, "p_r16": 0.0, "p_qf": 0.0, "p_sf": 0.0, "p_final": 0.0, "p_win": 0.0, "eliminated": true}, {"team": "Ecuador", "confederation": "CONMEBOL", "color": "#3fb950", "fifa_rank": 17, "p_r32": 1.0, "p_r16": 0.0, "p_qf": 0.0, "p_sf": 0.0, "p_final": 0.0, "p_win": 0.0, "eliminated": true}, {"team": "Netherlands", "confederation": "UEFA", "color": "#58a6ff", "fifa_rank": 8, "p_r32": 1.0, "p_r16": 0.0, "p_qf": 0.0, "p_sf": 0.0, "p_final": 0.0, "p_win": 0.0, "eliminated": true}, {"team": "Japan", "confederation": "AFC", "color": "#bc8cff", "fifa_rank": 12, "p_r32": 1.0, "p_r16": 0.0, "p_qf": 0.0, "p_sf": 0.0, "p_final": 0.0, "p_win": 0.0, "eliminated": true}, {"team": "Sweden", "confederation": "UEFA", "color": "#58a6ff", "fifa_rank": 26, "p_r32": 1.0, "p_r16": 0.0, "p_qf": 0.0, "p_sf": 0.0, "p_final": 0.0, "p_win": 0.0, "eliminated": true}, {"team": "Tunisia", "confederation": "CAF", "color": "#d29922", "fifa_rank": 35, "p_r32": 0.0, "p_r16": 0.0, "p_qf": 0.0, "p_sf": 0.0, "p_final": 0.0, "p_win": 0.0, "eliminated": true}, {"team": "Iran", "confederation": "AFC", "color": "#bc8cff", "fifa_rank": 34, "p_r32": 0.0, "p_r16": 0.0, "p_qf": 0.0, "p_sf": 0.0, "p_final": 0.0, "p_win": 0.0, "eliminated": true}, {"team": "New Zealand", "confederation": "OFC", "color": "#8b949e", "fifa_rank": 40, "p_r32": 0.0, "p_r16": 0.0, "p_qf": 0.0, "p_sf": 0.0, "p_final": 0.0, "p_win": 0.0, "eliminated": true}, {"team": "Saudi Arabia", "confederation": "AFC", "color": "#bc8cff", "fifa_rank": 36, "p_r32": 0.0, "p_r16": 0.0, "p_qf": 0.0, "p_sf": 0.0, "p_final": 0.0, "p_win": 0.0, "eliminated": true}, {"team": "Uruguay", "confederation": "CONMEBOL", "color": "#3fb950", "fifa_rank": 11, "p_r32": 0.0, "p_r16": 0.0, "p_qf": 0.0, "p_sf": 0.0, "p_final": 0.0, "p_win": 0.0, "eliminated": true}, {"team": "Senegal", "confederation": "CAF", "color": "#d29922", "fifa_rank": 21, "p_r32": 1.0, "p_r16": 0.0, "p_qf": 0.0, "p_sf": 0.0, "p_final": 0.0, "p_win": 0.0, "eliminated": true}, {"team": "Iraq", "confederation": "AFC", "color": "#bc8cff", "fifa_rank": 41, "p_r32": 0.0, "p_r16": 0.0, "p_qf": 0.0, "p_sf": 0.0, "p_final": 0.0, "p_win": 0.0, "eliminated": true}, {"team": "Algeria", "confederation": "CAF", "color": "#d29922", "fifa_rank": 27, "p_r32": 1.0, "p_r16": 0.0, "p_qf": 0.0, "p_sf": 0.0, "p_final": 0.0, "p_win": 0.0, "eliminated": true}, {"team": "Austria", "confederation": "UEFA", "color": "#58a6ff", "fifa_rank": 24, "p_r32": 1.0, "p_r16": 0.0, "p_qf": 0.0, "p_sf": 0.0, "p_final": 0.0, "p_win": 0.0, "eliminated": true}, {"team": "Jordan", "confederation": "AFC", "color": "#bc8cff", "fifa_rank": 42, "p_r32": 0.0, "p_r16": 0.0, "p_qf": 0.0, "p_sf": 0.0, "p_final": 0.0, "p_win": 0.0, "eliminated": true}, {"team": "DR Congo", "confederation": "CAF", "color": "#d29922", "fifa_rank": 44, "p_r32": 1.0, "p_r16": 0.0, "p_qf": 0.0, "p_sf": 0.0, "p_final": 0.0, "p_win": 0.0, "eliminated": true}, {"team": "Uzbekistan", "confederation": "AFC", "color": "#bc8cff", "fifa_rank": 46, "p_r32": 0.0, "p_r16": 0.0, "p_qf": 0.0, "p_sf": 0.0, "p_final": 0.0, "p_win": 0.0, "eliminated": true}, {"team": "Croatia", "confederation": "UEFA", "color": "#58a6ff", "fifa_rank": 15, "p_r32": 1.0, "p_r16": 0.0, "p_qf": 0.0, "p_sf": 0.0, "p_final": 0.0, "p_win": 0.0, "eliminated": true}, {"team": "Panama", "confederation": "CONCACAF", "color": "#f97316", "fifa_rank": 39, "p_r32": 0.0, "p_r16": 0.0, "p_qf": 0.0, "p_sf": 0.0, "p_final": 0.0, "p_win": 0.0, "eliminated": true}]}